[{"passengerId":"0xd5f5ef5ff4c6323c62bdc5ab2061f440aefc511b000000000000000000000000","passengerGeohash":"wx4epb8scg1","vehicleId":"0x91153bad44dcc46187c481d8d36a53e58522d0c4","vehicleStartPosition":"wx4ep8e5gw0","emptyAstarTime":1404,"emptyRoute":["wx4ep8e5gw0","wx4ep8e7ytm","wx4ep8eect7","wx4ep8eegvm","wx4ep8eevmq","wx4ep8egbj3","wx4ep8egftm","wx4ep8eguv6","wx4ep8s5cjq","wx4ep8s7gv1","wx4ep8t7vs6","wx4ep8tgc5y","wx4ep8wgyg3","wx4epb85u54","wx4epb8ecep","wx4epb8ev6c","wx4epb8sv73","wx4epb8scg1"],"emptyRouteTime":0,"emptyCountFrag":18,"endGeohash":"wx4ep8e5gw0","loadAstarTime":2580,"loadRoute":["wx4epb8scg1","wx4epb8hu4f","wx4ep8xsufs","wx4ep8tuc1y","wx4ep8tsy9y","wx4ep8skg7g","wx4ep8euzeg","wx4ep8euueu","wx4ep8eszuj","wx4ep8esvk5","wx4ep8esgsp","wx4ep8esch5","wx4ep8ekvs7","wx4ep8ehc9p","wx4ep88uvqz","wx4ep88hgzm","wx4ep2xtp80","wx4ep2xt08e","wx4ep2wm54f","wx4ep2sjrcj","wx4ep2sjk17","wx4ep2sj3cs","wx4ep2ev632","wx4ep2dv3gb","wx4ep2dt6k2","wx4ep2dmrhu","wx4ep2dkw5q","wx4ep2ds975","wx4ep2du9f8","wx4ep2eueb6","wx4ep2sh9b6","wx4ep2shebp","wx4ep2shxb7","wx4ep2xs0xg","wx4ep2xsprn","wx4ep88h5yj","wx4ep88ujm3","wx4ep8e5gw0"],"loadRouteTime":0,"loadCountFrag":38},{"passengerId":"0xf4190533e1203597f7cbe83cd76a32192af04ebf000000000000000000000000","passengerGeohash":"wx4epb8scg1","vehicleId":"0xad8a321e2e8f8f51245f47b8f412979d5740e625","vehicleStartPosition":"wx4ep8e5gw0","emptyAstarTime":996,"emptyRoute":["wx4ep8e5gw0","wx4ep8e7ytm","wx4ep8eect7","wx4ep8eegvm","wx4ep8eevmq","wx4ep8egbj3","wx4ep8egftm","wx4ep8eguv6","wx4ep8s5cjq","wx4ep8s7gv1","wx4ep8t7vs6","wx4ep8tgc5y","wx4ep8wgyg3","wx4epb85u54","wx4epb8ecep","wx4epb8ev6c","wx4epb8sv73","wx4epb8scg1"],"emptyRouteTime":0,"emptyCountFrag":18,"endGeohash":"wx4ep8e5gw0","loadAstarTime":1275,"loadRoute":["wx4epb8scg1","wx4epb8hu4f","wx4ep8xsufs","wx4ep8tuc1y","wx4ep8tsy9y","wx4ep8skg7g","wx4ep8euzeg","wx4ep8euueu","wx4ep8eszuj","wx4ep8esvk5","wx4ep8esgsp","wx4ep8esch5","wx4ep8ekvs7","wx4ep8ehc9p","wx4ep88uvqz","wx4ep88hgzm","wx4ep2xtp80","wx4ep2xt08e","wx4ep2wm54f","wx4ep2sjrcj","wx4ep2sjk17","wx4ep2sj3cs","wx4ep2ev632","wx4ep2dv3gb","wx4ep2dt6k2","wx4ep2dmrhu","wx4ep2dkw5q","wx4ep2ds975","wx4ep2du9f8","wx4ep2eueb6","wx4ep2sh9b6","wx4ep2shebp","wx4ep2shxb7","wx4ep2xs0xg","wx4ep2xsprn","wx4ep88h5yj","wx4ep88ujm3","wx4ep8e5gw0"],"loadRouteTime":0,"loadCountFrag":38},{"passengerId":"0x7a68b86008b0cfc3ae0e8068360271cbb999c97d000000000000000000000000","passengerGeohash":"wx4epb8scg1","vehicleId":"0x91153bad44dcc46187c481d8d36a53e58522d0c4","vehicleStartPosition":"wx4ep8e5gw0","emptyAstarTime":153,"emptyRoute":["wx4ep8e5gw0","wx4ep8e7ytm","wx4ep8eect7","wx4ep8eegvm","wx4ep8eevmq","wx4ep8egbj3","wx4ep8egftm","wx4ep8eguv6","wx4ep8s5cjq","wx4ep8s7gv1","wx4ep8t7vs6","wx4ep8tgc5y","wx4ep8wgyg3","wx4epb85u54","wx4epb8ecep","wx4epb8ev6c","wx4epb8sv73","wx4epb8scg1"],"emptyRouteTime":0,"emptyCountFrag":18,"endGeohash":"wx4ep8e5gw0","loadAstarTime":2621,"loadRoute":["wx4epb8scg1","wx4epb8hu4f","wx4ep8xsufs","wx4ep8tuc1y","wx4ep8tsy9y","wx4ep8skg7g","wx4ep8euzeg","wx4ep8euueu","wx4ep8eszuj","wx4ep8esvk5","wx4ep8esgsp","wx4ep8esch5","wx4ep8ekvs7","wx4ep8ehc9p","wx4ep88uvqz","wx4ep88hgzm","wx4ep2xtp80","wx4ep2xt08e","wx4ep2wm54f","wx4ep2sjrcj","wx4ep2sjk17","wx4ep2sj3cs","wx4ep2ev632","wx4ep2dv3gb","wx4ep2dt6k2","wx4ep2dmrhu","wx4ep2dkw5q","wx4ep2ds975","wx4ep2du9f8","wx4ep2eueb6","wx4ep2sh9b6","wx4ep2shebp","wx4ep2shxb7","wx4ep2xs0xg","wx4ep2xsprn","wx4ep88h5yj","wx4ep88ujm3","wx4ep8e5gw0"],"loadRouteTime":0,"loadCountFrag":38},{"passengerId":"0xe64e81bc77ee05caaa6b1476de75193607e84d87000000000000000000000000","passengerGeohash":"wx4epb8scg1","vehicleId":"0xad8a321e2e8f8f51245f47b8f412979d5740e625","vehicleStartPosition":"wx4ep8e5gw0","emptyAstarTime":754,"emptyRoute":["wx4ep8e5gw0","wx4ep8e7ytm","wx4ep8eect7","wx4ep8eegvm","wx4ep8eevmq","wx4ep8egbj3","wx4ep8egftm","wx4ep8eguv6","wx4ep8s5cjq","wx4ep8s7gv1","wx4ep8t7vs6","wx4ep8tgc5y","wx4ep8wgyg3","wx4epb85u54","wx4epb8ecep","wx4epb8ev6c","wx4epb8sv73","wx4epb8scg1"],"emptyRouteTime":0,"emptyCountFrag":18,"endGeohash":"wx4ep8e5gw0","loadAstarTime":2518,"loadRoute":["wx4epb8scg1","wx4epb8hu4f","wx4ep8xsufs","wx4ep8tuc1y","wx4ep8tsy9y","wx4ep8skg7g","wx4ep8euzeg","wx4ep8euueu","wx4ep8eszuj","wx4ep8esvk5","wx4ep8esgsp","wx4ep8esch5","wx4ep8ekvs7","wx4ep8ehc9p","wx4ep88uvqz","wx4ep88hgzm","wx4ep2xtp80","wx4ep2xt08e","wx4ep2wm54f","wx4ep2sjrcj","wx4ep2sjk17","wx4ep2sj3cs","wx4ep2ev632","wx4ep2dv3gb","wx4ep2dt6k2","wx4ep2dmrhu","wx4ep2dkw5q","wx4ep2ds975","wx4ep2du9f8","wx4ep2eueb6","wx4ep2sh9b6","wx4ep2shebp","wx4ep2shxb7","wx4ep2xs0xg","wx4ep2xsprn","wx4ep88h5yj","wx4ep88ujm3","wx4ep8e5gw0"],"loadRouteTime":0,"loadCountFrag":38}]